quicklogging/__init__.py
quicklogging/base.py
quicklogging/stream_wrapper.py
quicklogging-0.4.dist-info/LICENSE
quicklogging-0.4.dist-info/METADATA
quicklogging-0.4.dist-info/WHEEL
quicklogging-0.4.dist-info/top_level.txt
quicklogging-0.4.dist-info/RECORD
