Metadata-Version: 2.1
Name: quicklogging
Version: 0.4
Summary: logging made easy, can convert print() calls into logs without changing code
Home-page: UNKNOWN
Author: "Feth AREZKI (majerti)"
Author-email: "feth.arezki@majerti.fr"
License: UNKNOWN
Platform: UNKNOWN
Classifier: License :: OSI Approved :: MIT License
Classifier: Programming Language :: Python :: 3
Classifier: Operating System :: OS Independent
Classifier: Development Status :: 5 - Production/Stable
Classifier: Topic :: System :: Logging
Classifier: Topic :: Software Development :: Libraries
Classifier: Topic :: Software Development :: Libraries :: Python Modules
License-File: LICENSE
Provides-Extra: test
Requires-Dist: pytest ; extra == 'test'
Requires-Dist: pytest-cov ; extra == 'test'
Requires-Dist: pytest-runner ; extra == 'test'
Requires-Dist: six ; extra == 'test'
Requires-Dist: stringimporter (>=0.1.3) ; extra == 'test'
